spacecases_common/__init__.py
spacecases_common/py.typed
spacecases_common-0.14.2.dist-info/LICENSE
spacecases_common-0.14.2.dist-info/METADATA
spacecases_common-0.14.2.dist-info/WHEEL
spacecases_common-0.14.2.dist-info/top_level.txt
spacecases_common-0.14.2.dist-info/RECORD
