Metadata-Version: 2.2
Name: spacecases-common
Version: 0.14.2
Summary: Common code shared across SpaceCases projects
Author-email: William Redding <williamdredding@proton.me>
License: GPL-3 license
Project-URL: homepage, https://github.com/username/spacecases-common
Classifier: Programming Language :: Python :: 3
Classifier: License :: OSI Approved :: GNU General Public License v3 (GPLv3)
Classifier: Operating System :: OS Independent
Requires-Python: >=3.12
License-File: LICENSE
Requires-Dist: ruff==0.8.4
Requires-Dist: mypy==1.14.0
Requires-Dist: discord.py==2.4.0
Requires-Dist: pydantic==2.10.4
Requires-Dist: aiohttp==3.11.11
